{
	"song": {
		"player1": "dad",
		"gfVersion": "gf",
		"notes": [
			{
				"sectionBeats": 4,
				"sectionNotes": [],
				"typeOfSection": 0,
				"gfSection": false,
				"altAnim": false,
				"mustHitSection": true,
				"changeBPM": false,
				"bpm": 150
			},
			{
				"sectionBeats": 4,
				"sectionNotes": [
					[
						1714.28571428571,
						7,
						321.428571428571
					],
					[
						2250,
						3,
						0
					],
					[
						1928.57142857143,
						0,
						0
					],
					[
						2035.71428571429,
						2,
						0
					],
					[
						2142.85714285714,
						1,
						0
					],
					[
						2357.14285714286,
						0,
						0
					],
					[
						2410.71428571429,
						2,
						0
					],
					[
						2571.42857142857,
						3,
						0
					],
					[
						2785.71428571429,
						1,
						0
					],
					[
						3000,
						2,
						0
					],
					[
						3214.28571428571,
						0,
						0
					]
				],
				"typeOfSection": 0,
				"gfSection": false,
				"altAnim": false,
				"mustHitSection": true,
				"changeBPM": false,
				"bpm": 150
			},
			{
				"sectionBeats": 4,
				"sectionNotes": [
					[
						4285.71428571429,
						7,
						0
					],
					[
						4500,
						4,
						0
					],
					[
						4714.28571428571,
						6,
						0
					],
					[
						4928.57142857143,
						5,
						0
					],
					[
						4928.57142857143,
						4,
						0
					],
					[
						3428.57142857143,
						2,
						0
					],
					[
						3642.85714285714,
						3,
						0
					],
					[
						3857.14285714286,
						1,
						0
					],
					[
						3964.28571428571,
						2,
						0
					],
					[
						4071.42857142857,
						0,
						0
					],
					[
						4285.71428571429,
						3,
						0
					],
					[
						4500,
						0,
						0
					],
					[
						4607.14285714286,
						1,
						0
					],
					[
						4714.28571428571,
						2,
						0
					],
					[
						4928.57142857143,
						1,
						0
					],
					[
						4982.14285714286,
						3,
						0
					],
					[
						4928.57142857143,
						0,
						0
					]
				],
				"typeOfSection": 0,
				"gfSection": false,
				"altAnim": false,
				"mustHitSection": true,
				"changeBPM": false,
				"bpm": 140
			},
			{
				"sectionBeats": 4,
				"sectionNotes": [
					[
						5142.85714285714,
						7,
						321.428571428571
					],
					[
						5142.85714285714,
						6,
						0
					],
					[
						5142.85714285714,
						2,
						0
					],
					[
						5571.42857142857,
						0,
						0
					],
					[
						5785.71428571429,
						1,
						0
					],
					[
						5892.85714285714,
						2,
						0
					],
					[
						6000,
						3,
						0
					],
					[
						6214.28571428571,
						0,
						0
					],
					[
						6428.57142857143,
						2,
						0
					],
					[
						6642.85714285714,
						3,
						0
					],
					[
						6750,
						3,
						0
					],
					[
						5142.85714285714,
						1,
						0
					],
					[
						5357.14285714286,
						3,
						0
					]
				],
				"typeOfSection": 0,
				"gfSection": false,
				"altAnim": false,
				"mustHitSection": true,
				"changeBPM": false,
				"bpm": 140
			},
			{
				"sectionBeats": 4,
				"sectionNotes": [
					[
						7714.28571428571,
						4,
						0
					],
					[
						7928.57142857143,
						6,
						0
					],
					[
						8142.85714285714,
						7,
						0
					],
					[
						8357.14285714286,
						6,
						0
					],
					[
						7714.28571428571,
						5,
						0
					],
					[
						8142.85714285714,
						4,
						0
					],
					[
						6857.14285714286,
						1,
						0
					],
					[
						7071.42857142857,
						0,
						0
					],
					[
						7178.57142857143,
						1,
						0
					],
					[
						7285.71428571429,
						2,
						0
					],
					[
						7392.85714285714,
						1,
						0
					],
					[
						7500,
						0,
						0
					],
					[
						7607.14285714286,
						1,
						0
					],
					[
						7714.28571428571,
						3,
						0
					],
					[
						7928.57142857143,
						3,
						0
					],
					[
						8142.85714285714,
						2,
						0
					],
					[
						8357.14285714286,
						0,
						0
					],
					[
						7714.28571428571,
						2,
						0
					],
					[
						8142.85714285714,
						1,
						0
					]
				],
				"typeOfSection": 0,
				"gfSection": false,
				"altAnim": false,
				"mustHitSection": true,
				"changeBPM": false,
				"bpm": 140
			},
			{
				"sectionBeats": 4,
				"sectionNotes": [
					[
						9214.28571428571,
						0,
						0
					],
					[
						9428.57142857143,
						3,
						0
					],
					[
						9642.85714285714,
						2,
						0
					],
					[
						8571.42857142857,
						1,
						321.428571428571
					],
					[
						10071.4285714286,
						0,
						0
					],
					[
						8571.42857142857,
						0,
						0
					],
					[
						9428.57142857143,
						1,
						0
					],
					[
						8571.42857142857,
						7,
						0
					],
					[
						8785.71428571428,
						5,
						0
					],
					[
						9000,
						7,
						0
					],
					[
						9214.28571428571,
						6,
						0
					],
					[
						9642.85714285714,
						6,
						0
					],
					[
						9857.14285714286,
						5,
						0
					],
					[
						8571.42857142857,
						6,
						0
					],
					[
						9000,
						4,
						0
					],
					[
						9428.57142857143,
						5,
						0
					],
					[
						9428.57142857143,
						4,
						0
					],
					[
						9857.14285714286,
						7,
						0
					]
				],
				"typeOfSection": 0,
				"gfSection": false,
				"altAnim": false,
				"mustHitSection": false,
				"changeBPM": false,
				"bpm": 140
			},
			{
				"sectionBeats": 4,
				"sectionNotes": [
					[
						10500,
						2,
						0
					],
					[
						10928.5714285714,
						1,
						0
					],
					[
						11357.1428571429,
						3,
						0
					],
					[
						11571.4285714286,
						0,
						0
					],
					[
						11785.7142857143,
						3,
						0
					],
					[
						11571.4285714286,
						2,
						0
					],
					[
						10285.7142857143,
						6,
						0
					],
					[
						10714.2857142857,
						7,
						0
					],
					[
						10928.5714285714,
						6,
						0
					],
					[
						11142.8571428571,
						6,
						0
					],
					[
						11357.1428571429,
						4,
						0
					],
					[
						11571.4285714286,
						5,
						0
					],
					[
						10285.7142857143,
						5,
						0
					],
					[
						10714.2857142857,
						4,
						0
					],
					[
						11142.8571428571,
						7,
						0
					],
					[
						11571.4285714286,
						6,
						0
					]
				],
				"typeOfSection": 0,
				"gfSection": false,
				"altAnim": false,
				"mustHitSection": false,
				"changeBPM": false,
				"bpm": 140
			},
			{
				"sectionBeats": 4,
				"sectionNotes": [
					[
						12000,
						1,
						0
					],
					[
						12214.2857142857,
						1,
						0
					],
					[
						12642.8571428571,
						2,
						0
					],
					[
						13071.4285714286,
						2,
						0
					],
					[
						13285.7142857143,
						1,
						0
					],
					[
						13500,
						2,
						0
					],
					[
						12000,
						0,
						0
					],
					[
						12428.5714285714,
						3,
						0
					],
					[
						12857.1428571429,
						0,
						0
					],
					[
						12857.1428571429,
						1,
						0
					],
					[
						12428.5714285714,
						2,
						0
					],
					[
						13285.7142857143,
						0,
						0
					],
					[
						12000,
						7,
						0
					],
					[
						12214.2857142857,
						4,
						0
					],
					[
						12428.5714285714,
						6,
						0
					],
					[
						12642.8571428571,
						4,
						0
					],
					[
						12750,
						5,
						0
					],
					[
						12857.1428571429,
						7,
						0
					],
					[
						13285.7142857143,
						7,
						0
					],
					[
						13392.8571428571,
						5,
						0
					],
					[
						13500,
						4,
						0
					],
					[
						12000,
						6,
						0
					],
					[
						12428.5714285714,
						5,
						0
					],
					[
						12857.1428571429,
						6,
						0
					],
					[
						13285.7142857143,
						6,
						0
					],
					[
						13071.4285714286,
						4,
						0
					]
				],
				"typeOfSection": 0,
				"gfSection": false,
				"altAnim": false,
				"mustHitSection": false,
				"changeBPM": false,
				"bpm": 140
			},
			{
				"sectionBeats": 4,
				"sectionNotes": [
					[
						13714.2857142857,
						3,
						0
					],
					[
						13928.5714285714,
						0,
						0
					],
					[
						14142.8571428571,
						3,
						0
					],
					[
						14357.1428571429,
						0,
						0
					],
					[
						14571.4285714286,
						1,
						0
					],
					[
						14785.7142857143,
						2,
						0
					],
					[
						15000,
						3,
						0
					],
					[
						13714.2857142857,
						1,
						0
					],
					[
						14142.8571428571,
						2,
						0
					],
					[
						14571.4285714286,
						3,
						0
					],
					[
						15000,
						0,
						0
					],
					[
						13714.2857142857,
						5,
						0
					],
					[
						13928.5714285714,
						7,
						0
					],
					[
						14142.8571428571,
						6,
						0
					],
					[
						14785.7142857143,
						6,
						0
					],
					[
						15000,
						5,
						0
					],
					[
						15160.7142857143,
						6,
						0
					],
					[
						15267.8571428571,
						7,
						0
					],
					[
						13714.2857142857,
						6,
						0
					],
					[
						14142.8571428571,
						4,
						0
					],
					[
						14357.1428571429,
						5,
						0
					],
					[
						14571.4285714286,
						4,
						0
					],
					[
						14571.4285714286,
						7,
						0
					],
					[
						15000,
						4,
						0
					]
				],
				"typeOfSection": 0,
				"gfSection": false,
				"altAnim": false,
				"mustHitSection": false,
				"changeBPM": false,
				"bpm": 140
			},
			{
				"sectionBeats": 4,
				"sectionNotes": [
					[
						15857.1428571429,
						0,
						0
					],
					[
						16071.4285714286,
						2,
						0
					],
					[
						16285.7142857143,
						1,
						0
					],
					[
						16500,
						1,
						0
					],
					[
						16714.2857142857,
						3,
						0
					],
					[
						16928.5714285714,
						0,
						0
					],
					[
						16285.7142857143,
						0,
						0
					]
				],
				"typeOfSection": 0,
				"gfSection": false,
				"altAnim": false,
				"mustHitSection": true,
				"changeBPM": false,
				"bpm": 140
			},
			{
				"sectionBeats": 4,
				"sectionNotes": [
					[
						17142.8571428571,
						1,
						0
					],
					[
						17357.1428571429,
						3,
						0
					],
					[
						18000,
						2,
						321.428571428571
					],
					[
						17571.4285714286,
						1,
						0
					],
					[
						17785.7142857143,
						0,
						0
					],
					[
						18428.5714285714,
						1,
						0
					],
					[
						18482.1428571429,
						3,
						0
					],
					[
						18642.8571428571,
						2,
						0
					],
					[
						18000,
						3,
						0
					]
				],
				"typeOfSection": 0,
				"gfSection": false,
				"altAnim": false,
				"mustHitSection": true,
				"changeBPM": false,
				"bpm": 140
			},
			{
				"sectionBeats": 4,
				"sectionNotes": [
					[
						18857.1428571429,
						0,
						0
					],
					[
						19071.4285714286,
						1,
						0
					],
					[
						19285.7142857143,
						0,
						0
					],
					[
						19500,
						2,
						0
					],
					[
						19714.2857142857,
						3,
						0
					],
					[
						20142.8571428571,
						1,
						0
					],
					[
						20196.4285714286,
						0,
						0
					],
					[
						20357.1428571429,
						2,
						0
					],
					[
						19714.2857142857,
						1,
						0
					]
				],
				"typeOfSection": 0,
				"gfSection": false,
				"altAnim": false,
				"mustHitSection": true,
				"changeBPM": false,
				"bpm": 140
			},
			{
				"sectionBeats": 4,
				"sectionNotes": [
					[
						20571.4285714286,
						3,
						0
					],
					[
						20678.5714285714,
						0,
						0
					],
					[
						20785.7142857143,
						1,
						0
					],
					[
						21321.4285714286,
						1,
						0
					],
					[
						21428.5714285714,
						2,
						0
					],
					[
						21214.2857142857,
						0,
						0
					],
					[
						21000,
						3,
						0
					],
					[
						21857.1428571429,
						1,
						0
					],
					[
						21964.2857142857,
						2,
						0
					],
					[
						21428.5714285714,
						3,
						0
					]
				],
				"typeOfSection": 0,
				"gfSection": false,
				"altAnim": false,
				"mustHitSection": true,
				"changeBPM": false,
				"bpm": 140
			},
			{
				"sectionBeats": 4,
				"sectionNotes": [
					[
						22714.2857142857,
						3,
						0
					],
					[
						22928.5714285714,
						0,
						0
					],
					[
						23142.8571428571,
						3,
						321.428571428571
					],
					[
						23571.4285714286,
						1,
						0
					],
					[
						23785.7142857143,
						3,
						0
					],
					[
						23142.8571428571,
						2,
						0
					],
					[
						22285.7142857143,
						7,
						0
					]
				],
				"typeOfSection": 0,
				"gfSection": false,
				"altAnim": false,
				"mustHitSection": false,
				"changeBPM": false,
				"bpm": 140
			},
			{
				"sectionBeats": 4,
				"sectionNotes": [
					[
						24000,
						0,
						0
					],
					[
						24214.2857142857,
						1,
						0
					],
					[
						24428.5714285714,
						0,
						0
					],
					[
						24642.8571428571,
						1,
						0
					],
					[
						24857.1428571429,
						2,
						321.428571428571
					],
					[
						25285.7142857143,
						3,
						0
					],
					[
						25500,
						2,
						0
					],
					[
						24857.1428571429,
						3,
						0
					]
				],
				"typeOfSection": 0,
				"gfSection": false,
				"altAnim": false,
				"mustHitSection": false,
				"changeBPM": false,
				"bpm": 140
			},
			{
				"sectionBeats": 4,
				"sectionNotes": [
					[
						25714.2857142857,
						1,
						0
					],
					[
						25928.5714285714,
						0,
						0
					],
					[
						26035.7142857143,
						3,
						0
					],
					[
						26142.8571428571,
						1,
						0
					],
					[
						26357.1428571429,
						3,
						0
					],
					[
						26571.4285714286,
						0,
						0
					],
					[
						26785.7142857143,
						3,
						0
					],
					[
						27000,
						0,
						0
					],
					[
						27214.2857142857,
						3,
						0
					],
					[
						26571.4285714286,
						1,
						0
					]
				],
				"typeOfSection": 0,
				"gfSection": false,
				"altAnim": false,
				"mustHitSection": false,
				"changeBPM": false,
				"bpm": 140
			},
			{
				"sectionBeats": 4,
				"sectionNotes": [
					[
						27642.8571428571,
						1,
						0
					],
					[
						28285.7142857143,
						2,
						0
					],
					[
						27857.1428571429,
						0,
						0
					],
					[
						28071.4285714286,
						1,
						0
					],
					[
						28714.2857142857,
						3,
						0
					],
					[
						27428.5714285714,
						0,
						0
					],
					[
						28285.7142857143,
						3,
						0
					]
				],
				"typeOfSection": 0,
				"gfSection": false,
				"altAnim": false,
				"mustHitSection": false,
				"changeBPM": false,
				"bpm": 140
			},
			{
				"sectionBeats": 4,
				"sectionNotes": [
					[
						29357.1428571429,
						0,
						0
					],
					[
						29571.4285714286,
						1,
						0
					],
					[
						29785.7142857143,
						0,
						0
					],
					[
						30000,
						2,
						0
					],
					[
						30214.2857142857,
						3,
						0
					],
					[
						30321.4285714286,
						2,
						0
					],
					[
						30428.5714285714,
						0,
						0
					],
					[
						30642.8571428571,
						1,
						0
					],
					[
						30750,
						2,
						0
					],
					[
						30000,
						1,
						0
					]
				],
				"typeOfSection": 0,
				"gfSection": false,
				"altAnim": false,
				"mustHitSection": true,
				"changeBPM": false,
				"bpm": 140
			},
			{
				"sectionBeats": 4,
				"sectionNotes": [
					[
						30857.1428571429,
						3,
						0
					],
					[
						31071.4285714286,
						2,
						0
					],
					[
						31285.7142857143,
						0,
						0
					],
					[
						31500,
						1,
						0
					],
					[
						31607.1428571429,
						3,
						0
					],
					[
						31714.2857142857,
						2,
						0
					],
					[
						31928.5714285714,
						1,
						0
					],
					[
						32142.8571428571,
						3,
						0
					],
					[
						32357.1428571429,
						1,
						0
					],
					[
						32464.2857142857,
						3,
						0
					],
					[
						31714.2857142857,
						0,
						0
					],
					[
						31982.1428571429,
						2,
						0
					]
				],
				"typeOfSection": 0,
				"gfSection": false,
				"altAnim": false,
				"mustHitSection": true,
				"changeBPM": false,
				"bpm": 140
			},
			{
				"sectionBeats": 4,
				"sectionNotes": [
					[
						32571.4285714286,
						0,
						0
					],
					[
						32785.7142857143,
						2,
						0
					],
					[
						32892.8571428571,
						1,
						0
					],
					[
						33000,
						3,
						0
					],
					[
						33107.1428571428,
						2,
						0
					],
					[
						33214.2857142857,
						0,
						0
					],
					[
						33321.4285714286,
						1,
						0
					],
					[
						33428.5714285714,
						3,
						0
					],
					[
						33535.7142857143,
						0,
						0
					],
					[
						33642.8571428571,
						1,
						0
					],
					[
						33750,
						2,
						0
					],
					[
						33857.1428571428,
						0,
						0
					],
					[
						33964.2857142857,
						3,
						0
					],
					[
						34071.4285714286,
						1,
						0
					],
					[
						34178.5714285714,
						2,
						0
					],
					[
						33428.5714285714,
						2,
						0
					]
				],
				"typeOfSection": 0,
				"gfSection": false,
				"altAnim": false,
				"mustHitSection": true,
				"changeBPM": false,
				"bpm": 140
			},
			{
				"sectionBeats": 4,
				"sectionNotes": [
					[
						34285.7142857143,
						0,
						0
					],
					[
						34500,
						3,
						0
					],
					[
						34607.1428571429,
						1,
						0
					],
					[
						34714.2857142857,
						2,
						0
					],
					[
						35142.8571428571,
						0,
						0
					],
					[
						35357.1428571429,
						1,
						0
					],
					[
						35571.4285714286,
						0,
						0
					],
					[
						35785.7142857143,
						1,
						0
					],
					[
						34928.5714285714,
						3,
						0
					],
					[
						35142.8571428571,
						2,
						0
					]
				],
				"typeOfSection": 0,
				"gfSection": false,
				"altAnim": false,
				"mustHitSection": true,
				"changeBPM": false,
				"bpm": 140
			},
			{
				"sectionBeats": 4,
				"sectionNotes": [
					[
						36000,
						3,
						214.285714285714
					],
					[
						36857.1428571429,
						3,
						0
					],
					[
						37071.4285714286,
						3,
						0
					],
					[
						37285.7142857143,
						0,
						0
					],
					[
						37392.8571428571,
						3,
						0
					],
					[
						37607.1428571429,
						0,
						0
					],
					[
						36428.5714285714,
						2,
						0
					],
					[
						36750,
						0,
						0
					],
					[
						36535.7142857143,
						3,
						0
					],
					[
						36642.8571428571,
						1,
						0
					],
					[
						36857.1428571429,
						2,
						0
					],
					[
						36000,
						7,
						0
					]
				],
				"typeOfSection": 0,
				"gfSection": false,
				"altAnim": false,
				"mustHitSection": false,
				"changeBPM": false,
				"bpm": 140
			},
			{
				"sectionBeats": 4,
				"sectionNotes": [
					[
						37714.2857142857,
						3,
						214.285714285714
					],
					[
						38142.8571428571,
						2,
						0
					],
					[
						38571.4285714286,
						3,
						0
					],
					[
						38785.7142857143,
						3,
						0
					],
					[
						39107.1428571429,
						3,
						0
					],
					[
						39214.2857142857,
						1,
						0
					],
					[
						39321.4285714286,
						0,
						0
					],
					[
						38035.7142857143,
						0,
						0
					],
					[
						38464.2857142857,
						0,
						0
					],
					[
						38250,
						3,
						0
					],
					[
						38357.1428571429,
						1,
						0
					],
					[
						38892.8571428571,
						2,
						0
					],
					[
						39000,
						0,
						0
					],
					[
						38571.4285714286,
						2,
						0
					],
					[
						39000,
						5,
						0
					]
				],
				"typeOfSection": 0,
				"gfSection": false,
				"altAnim": false,
				"mustHitSection": false,
				"changeBPM": false,
				"bpm": 140
			},
			{
				"sectionBeats": 4,
				"sectionNotes": [
					[
						39428.5714285714,
						3,
						0
					],
					[
						39642.8571428572,
						2,
						0
					],
					[
						39750,
						0,
						0
					],
					[
						39857.1428571429,
						1,
						0
					],
					[
						39964.2857142857,
						3,
						0
					],
					[
						40071.4285714286,
						0,
						0
					],
					[
						40285.7142857143,
						2,
						0
					],
					[
						40500,
						3,
						0
					],
					[
						40714.2857142857,
						0,
						0
					],
					[
						40928.5714285714,
						3,
						0
					],
					[
						40285.7142857143,
						1,
						0
					],
					[
						39535.7142857143,
						1,
						0
					],
					[
						39428.5714285714,
						7,
						0
					]
				],
				"typeOfSection": 0,
				"gfSection": false,
				"altAnim": false,
				"mustHitSection": false,
				"changeBPM": false,
				"bpm": 140
			},
			{
				"sectionBeats": 4,
				"sectionNotes": [
					[
						41142.8571428572,
						1,
						0
					],
					[
						41357.1428571429,
						2,
						0
					],
					[
						41571.4285714286,
						3,
						0
					],
					[
						41785.7142857143,
						2,
						0
					],
					[
						42214.2857142857,
						1,
						0
					],
					[
						42000,
						0,
						0
					],
					[
						42428.5714285714,
						2,
						0
					],
					[
						42642.8571428572,
						1,
						0
					],
					[
						42000,
						3,
						0
					]
				],
				"typeOfSection": 0,
				"gfSection": false,
				"altAnim": false,
				"mustHitSection": false,
				"changeBPM": false,
				"bpm": 140
			},
			{
				"sectionBeats": 4,
				"sectionNotes": [
					[
						42857.1428571429,
						7,
						321.428571428571
					],
					[
						43392.8571428571,
						3,
						0
					],
					[
						43071.4285714286,
						0,
						0
					],
					[
						43178.5714285714,
						2,
						0
					],
					[
						43285.7142857143,
						1,
						0
					],
					[
						43500,
						0,
						0
					],
					[
						43553.5714285714,
						2,
						0
					],
					[
						43714.2857142857,
						3,
						0
					],
					[
						44142.8571428571,
						2,
						0
					],
					[
						44357.1428571429,
						0,
						0
					],
					[
						42857.1428571429,
						6,
						0
					],
					[
						43714.2857142857,
						1,
						0
					],
					[
						43928.5714285714,
						0,
						0
					]
				],
				"typeOfSection": 0,
				"gfSection": false,
				"altAnim": false,
				"mustHitSection": true,
				"changeBPM": false,
				"bpm": 140
			},
			{
				"sectionBeats": 4,
				"sectionNotes": [
					[
						45428.5714285714,
						7,
						0
					],
					[
						45642.8571428571,
						4,
						0
					],
					[
						45857.1428571429,
						6,
						0
					],
					[
						46071.4285714286,
						5,
						0
					],
					[
						44571.4285714286,
						2,
						0
					],
					[
						44785.7142857143,
						3,
						0
					],
					[
						45000,
						1,
						0
					],
					[
						45107.1428571429,
						2,
						0
					],
					[
						45214.2857142857,
						0,
						0
					],
					[
						45428.5714285714,
						3,
						0
					],
					[
						45642.8571428571,
						0,
						0
					],
					[
						45750,
						1,
						0
					],
					[
						45857.1428571429,
						2,
						0
					],
					[
						46071.4285714286,
						1,
						0
					],
					[
						46125,
						3,
						0
					],
					[
						45428.5714285714,
						5,
						0
					],
					[
						45428.5714285714,
						2,
						0
					]
				],
				"typeOfSection": 0,
				"gfSection": false,
				"altAnim": false,
				"mustHitSection": true,
				"changeBPM": false,
				"bpm": 140
			},
			{
				"sectionBeats": 4,
				"sectionNotes": [
					[
						46285.7142857143,
						7,
						321.428571428571
					],
					[
						46285.7142857143,
						2,
						0
					],
					[
						46500,
						1,
						0
					],
					[
						46714.2857142857,
						0,
						0
					],
					[
						46928.5714285714,
						1,
						0
					],
					[
						47035.7142857143,
						2,
						0
					],
					[
						47142.8571428571,
						3,
						0
					],
					[
						47571.4285714286,
						2,
						0
					],
					[
						47785.7142857143,
						3,
						0
					],
					[
						47892.8571428571,
						3,
						0
					],
					[
						47142.8571428572,
						0,
						0
					],
					[
						47357.1428571429,
						1,
						0
					]
				],
				"typeOfSection": 0,
				"gfSection": false,
				"altAnim": false,
				"mustHitSection": true,
				"changeBPM": false,
				"bpm": 140
			},
			{
				"sectionBeats": 4,
				"sectionNotes": [
					[
						48857.1428571429,
						4,
						0
					],
					[
						49071.4285714286,
						6,
						0
					],
					[
						49285.7142857143,
						7,
						0
					],
					[
						49500,
						6,
						0
					],
					[
						48857.1428571429,
						5,
						0
					],
					[
						48000,
						1,
						0
					],
					[
						48214.2857142857,
						0,
						0
					],
					[
						48321.4285714286,
						1,
						0
					],
					[
						48428.5714285714,
						2,
						0
					],
					[
						48535.7142857143,
						1,
						0
					],
					[
						48642.8571428571,
						0,
						0
					],
					[
						48750,
						1,
						0
					],
					[
						48857.1428571429,
						3,
						0
					],
					[
						49071.4285714286,
						3,
						0
					],
					[
						49285.7142857143,
						2,
						0
					],
					[
						49500,
						0,
						0
					],
					[
						48857.1428571429,
						2,
						0
					]
				],
				"typeOfSection": 0,
				"gfSection": false,
				"altAnim": false,
				"mustHitSection": true,
				"changeBPM": false,
				"bpm": 140
			},
			{
				"sectionBeats": 4,
				"sectionNotes": [
					[
						50357.1428571429,
						0,
						0
					],
					[
						50571.4285714286,
						3,
						0
					],
					[
						50785.7142857143,
						2,
						0
					],
					[
						49714.2857142857,
						1,
						321.428571428571
					],
					[
						51214.2857142857,
						0,
						0
					],
					[
						50571.4285714286,
						1,
						0
					],
					[
						49714.2857142857,
						7,
						0
					],
					[
						49928.5714285714,
						5,
						0
					],
					[
						50142.8571428571,
						7,
						0
					],
					[
						50357.1428571429,
						6,
						0
					],
					[
						50785.7142857143,
						6,
						0
					],
					[
						50571.4285714286,
						4,
						0
					],
					[
						51000,
						5,
						0
					],
					[
						50571.4285714286,
						5,
						0
					]
				],
				"typeOfSection": 0,
				"gfSection": false,
				"altAnim": false,
				"mustHitSection": false,
				"changeBPM": false,
				"bpm": 140
			},
			{
				"sectionBeats": 4,
				"sectionNotes": [
					[
						51642.8571428571,
						2,
						0
					],
					[
						52071.4285714286,
						1,
						0
					],
					[
						52500,
						3,
						0
					],
					[
						52714.2857142857,
						0,
						0
					],
					[
						52928.5714285714,
						3,
						0
					],
					[
						51428.5714285714,
						6,
						0
					],
					[
						51857.1428571429,
						7,
						0
					],
					[
						52071.4285714286,
						6,
						0
					],
					[
						52285.7142857143,
						6,
						0
					],
					[
						52285.7142857143,
						4,
						0
					],
					[
						52500,
						5,
						0
					],
					[
						52714.2857142857,
						4,
						0
					]
				],
				"typeOfSection": 0,
				"gfSection": false,
				"altAnim": false,
				"mustHitSection": false,
				"changeBPM": false,
				"bpm": 140
			},
			{
				"sectionBeats": 4,
				"sectionNotes": [
					[
						53142.8571428571,
						1,
						0
					],
					[
						53357.1428571429,
						1,
						0
					],
					[
						53785.7142857143,
						2,
						0
					],
					[
						54214.2857142857,
						2,
						0
					],
					[
						54642.8571428571,
						2,
						0
					],
					[
						53571.4285714286,
						3,
						0
					],
					[
						54000,
						0,
						0
					],
					[
						54428.5714285714,
						0,
						0
					],
					[
						53142.8571428571,
						7,
						0
					],
					[
						53357.1428571429,
						4,
						0
					],
					[
						53571.4285714286,
						6,
						0
					],
					[
						53785.7142857143,
						4,
						0
					],
					[
						53892.8571428571,
						5,
						0
					],
					[
						54000,
						7,
						0
					],
					[
						54428.5714285714,
						7,
						0
					],
					[
						54535.7142857143,
						5,
						0
					],
					[
						54642.8571428571,
						4,
						0
					],
					[
						54000,
						3,
						0
					],
					[
						54000,
						6,
						0
					],
					[
						54214.2857142857,
						4,
						0
					]
				],
				"typeOfSection": 0,
				"gfSection": false,
				"altAnim": false,
				"mustHitSection": false,
				"changeBPM": false,
				"bpm": 140
			},
			{
				"sectionBeats": 4,
				"sectionNotes": [
					[
						54857.1428571429,
						3,
						0
					],
					[
						55071.4285714286,
						0,
						0
					],
					[
						55285.7142857143,
						3,
						0
					],
					[
						55500,
						0,
						0
					],
					[
						55714.2857142857,
						1,
						0
					],
					[
						55928.5714285714,
						2,
						0
					],
					[
						55714.2857142857,
						3,
						0
					],
					[
						56142.8571428571,
						0,
						0
					],
					[
						54857.1428571429,
						5,
						0
					],
					[
						55071.4285714286,
						7,
						0
					],
					[
						55285.7142857143,
						6,
						0
					],
					[
						55500,
						4,
						0
					],
					[
						55714.2857142857,
						5,
						0
					],
					[
						55928.5714285714,
						6,
						0
					],
					[
						56142.8571428571,
						5,
						0
					],
					[
						56303.5714285714,
						6,
						0
					],
					[
						56410.7142857143,
						7,
						0
					],
					[
						55714.2857142857,
						7,
						0
					]
				],
				"typeOfSection": 0,
				"gfSection": false,
				"altAnim": false,
				"mustHitSection": false,
				"changeBPM": false,
				"bpm": 140
			},
			{
				"sectionBeats": 4,
				"sectionNotes": [
					[
						57428.5714285715,
						7,
						0
					],
					[
						57642.8571428572,
						4,
						0
					],
					[
						58071.4285714286,
						7,
						0
					],
					[
						57428.5714285715,
						6,
						0
					],
					[
						56571.4285714286,
						0,
						0
					],
					[
						56678.5714285715,
						3,
						0
					],
					[
						56785.7142857143,
						2,
						0
					],
					[
						56892.8571428572,
						1,
						0
					],
					[
						57000,
						3,
						0
					],
					[
						57428.5714285715,
						1,
						0
					],
					[
						57535.7142857143,
						2,
						0
					],
					[
						57642.8571428572,
						3,
						0
					],
					[
						57857.1428571429,
						2,
						0
					],
					[
						58071.4285714286,
						0,
						0
					],
					[
						58178.5714285715,
						1,
						0
					],
					[
						57428.5714285715,
						0,
						0
					],
					[
						57214.2857142858,
						2,
						0
					]
				],
				"typeOfSection": 0,
				"gfSection": false,
				"altAnim": false,
				"mustHitSection": true,
				"changeBPM": false,
				"bpm": 140
			},
			{
				"sectionBeats": 4,
				"sectionNotes": [
					[
						58285.7142857143,
						5,
						321.428571428571
					],
					[
						58714.2857142858,
						7,
						0
					],
					[
						59142.8571428572,
						4,
						0
					],
					[
						59571.4285714286,
						6,
						0
					],
					[
						59142.8571428572,
						5,
						0
					],
					[
						58285.7142857143,
						3,
						0
					],
					[
						58500,
						1,
						0
					],
					[
						58714.2857142858,
						2,
						0
					],
					[
						58928.5714285715,
						0,
						0
					],
					[
						59142.8571428572,
						1,
						0
					],
					[
						59250,
						2,
						0
					],
					[
						59357.1428571429,
						0,
						0
					],
					[
						59464.2857142858,
						3,
						0
					],
					[
						59571.4285714286,
						2,
						0
					],
					[
						59785.7142857143,
						1,
						0
					],
					[
						59142.8571428572,
						3,
						0
					]
				],
				"typeOfSection": 0,
				"gfSection": false,
				"altAnim": false,
				"mustHitSection": true,
				"changeBPM": false,
				"bpm": 140
			},
			{
				"sectionBeats": 4,
				"sectionNotes": [
					[
						60000,
						5,
						0
					],
					[
						60321.4285714286,
						4,
						0
					],
					[
						60642.8571428572,
						6,
						0
					],
					[
						61071.4285714286,
						7,
						0
					],
					[
						61285.7142857143,
						4,
						0
					],
					[
						60000,
						3,
						0
					],
					[
						60107.1428571429,
						2,
						0
					],
					[
						60214.2857142858,
						1,
						0
					],
					[
						60321.4285714286,
						2,
						0
					],
					[
						60428.5714285715,
						0,
						0
					],
					[
						60642.8571428572,
						1,
						0
					],
					[
						60964.2857142858,
						2,
						0
					],
					[
						61285.7142857143,
						3,
						0
					],
					[
						61500,
						2,
						0
					],
					[
						60857.1428571429,
						3,
						0
					],
					[
						60857.1428571429,
						0,
						0
					],
					[
						61071.4285714286,
						0,
						0
					],
					[
						61125,
						1,
						0
					]
				],
				"typeOfSection": 0,
				"gfSection": false,
				"altAnim": false,
				"mustHitSection": true,
				"changeBPM": false,
				"bpm": 140
			},
			{
				"sectionBeats": 4,
				"sectionNotes": [
					[
						61714.2857142858,
						5,
						0
					],
					[
						62035.7142857143,
						4,
						0
					],
					[
						62357.1428571429,
						6,
						0
					],
					[
						62785.7142857143,
						7,
						0
					],
					[
						63000,
						4,
						0
					],
					[
						63214.2857142858,
						7,
						0
					],
					[
						61714.2857142858,
						3,
						0
					],
					[
						61821.4285714286,
						1,
						0
					],
					[
						61928.5714285715,
						0,
						0
					],
					[
						62142.8571428572,
						2,
						0
					],
					[
						62250,
						3,
						0
					],
					[
						62571.4285714286,
						2,
						0
					],
					[
						62678.5714285715,
						3,
						0
					],
					[
						62785.7142857143,
						0,
						0
					],
					[
						62892.8571428572,
						1,
						0
					],
					[
						63000,
						3,
						0
					],
					[
						63107.1428571429,
						0,
						0
					],
					[
						63214.2857142858,
						2,
						0
					],
					[
						63321.4285714286,
						1,
						0
					],
					[
						62571.4285714286,
						1,
						0
					],
					[
						62357.1428571429,
						0,
						0
					]
				],
				"typeOfSection": 0,
				"gfSection": false,
				"altAnim": false,
				"mustHitSection": true,
				"changeBPM": false,
				"bpm": 140
			},
			{
				"sectionBeats": 4,
				"sectionNotes": [
					[
						63428.5714285715,
						2,
						0
					],
					[
						63535.7142857143,
						1,
						0
					],
					[
						63642.8571428572,
						0,
						0
					],
					[
						63750.0000000001,
						1,
						0
					],
					[
						63857.1428571429,
						3,
						0
					],
					[
						63964.2857142858,
						2,
						0
					],
					[
						64071.4285714286,
						1,
						0
					],
					[
						64285.7142857143,
						0,
						0
					],
					[
						64500.0000000001,
						2,
						0
					],
					[
						64714.2857142858,
						3,
						0
					],
					[
						64928.5714285715,
						2,
						0
					],
					[
						64178.5714285715,
						2,
						0
					],
					[
						64285.7142857143,
						3,
						0
					],
					[
						63428.5714285715,
						7,
						0
					],
					[
						63535.7142857143,
						6,
						0
					],
					[
						63857.1428571429,
						6,
						0
					],
					[
						63964.2857142858,
						5,
						0
					],
					[
						64071.4285714286,
						7,
						0
					],
					[
						64178.5714285715,
						4,
						0
					],
					[
						64285.7142857143,
						6,
						0
					],
					[
						64607.1428571429,
						4,
						0
					],
					[
						64821.4285714286,
						6,
						0
					],
					[
						64928.5714285715,
						5,
						0
					],
					[
						65035.7142857143,
						7,
						0
					],
					[
						64714.2857142858,
						7,
						0
					],
					[
						63642.8571428572,
						4,
						0
					],
					[
						63750.0000000001,
						5,
						0
					],
					[
						64285.7142857143,
						7,
						0
					],
					[
						64392.8571428572,
						5,
						0
					],
					[
						64500.0000000001,
						6,
						0
					]
				],
				"typeOfSection": 0,
				"gfSection": false,
				"altAnim": false,
				"mustHitSection": false,
				"changeBPM": false,
				"bpm": 140
			},
			{
				"sectionBeats": 4,
				"sectionNotes": [
					[
						65142.8571428572,
						1,
						321.428571428571
					],
					[
						66000.0000000001,
						3,
						321.428571428571
					],
					[
						66000.0000000001,
						0,
						0
					],
					[
						65142.8571428572,
						4,
						0
					],
					[
						65357.1428571429,
						6,
						0
					],
					[
						65464.2857142858,
						7,
						0
					],
					[
						65571.4285714286,
						6,
						0
					],
					[
						65678.5714285715,
						5,
						0
					],
					[
						65785.7142857143,
						4,
						0
					],
					[
						65892.8571428572,
						7,
						0
					],
					[
						66000.0000000001,
						5,
						0
					],
					[
						66107.1428571429,
						6,
						0
					],
					[
						66428.5714285715,
						5,
						0
					],
					[
						66642.8571428572,
						6,
						0
					],
					[
						66750.0000000001,
						5,
						0
					],
					[
						65250.0000000001,
						5,
						0
					],
					[
						66000.0000000001,
						4,
						0
					],
					[
						66214.2857142858,
						7,
						0
					],
					[
						66321.4285714286,
						4,
						0
					],
					[
						66535.7142857143,
						7,
						0
					]
				],
				"typeOfSection": 0,
				"gfSection": false,
				"altAnim": false,
				"mustHitSection": false,
				"changeBPM": false,
				"bpm": 140
			},
			{
				"sectionBeats": 4,
				"sectionNotes": [
					[
						66857.1428571429,
						2,
						0
					],
					[
						67071.4285714286,
						3,
						0
					],
					[
						67285.7142857143,
						2,
						0
					],
					[
						67500.0000000001,
						0,
						0
					],
					[
						67714.2857142858,
						2,
						0
					],
					[
						67928.5714285715,
						3,
						0
					],
					[
						68142.8571428572,
						2,
						0
					],
					[
						68357.1428571429,
						0,
						0
					],
					[
						67714.2857142858,
						1,
						0
					],
					[
						66857.1428571429,
						6,
						0
					],
					[
						66964.2857142858,
						7,
						0
					],
					[
						67071.4285714286,
						5,
						0
					],
					[
						67178.5714285715,
						4,
						0
					],
					[
						67285.7142857143,
						5,
						0
					],
					[
						67392.8571428572,
						6,
						0
					],
					[
						67500.0000000001,
						4,
						0
					],
					[
						67607.1428571429,
						7,
						0
					],
					[
						67714.2857142858,
						5,
						0
					],
					[
						67821.4285714286,
						4,
						0
					],
					[
						67928.5714285715,
						6,
						0
					],
					[
						68035.7142857143,
						5,
						0
					],
					[
						68142.8571428572,
						7,
						0
					],
					[
						68250.0000000001,
						6,
						0
					],
					[
						68357.1428571429,
						4,
						0
					],
					[
						68464.2857142858,
						5,
						0
					],
					[
						67714.2857142858,
						6,
						0
					]
				],
				"typeOfSection": 0,
				"gfSection": false,
				"altAnim": false,
				"mustHitSection": false,
				"changeBPM": false,
				"bpm": 140
			},
			{
				"sectionBeats": 4,
				"sectionNotes": [
					[
						68571.4285714286,
						1,
						0
					],
					[
						68785.7142857143,
						2,
						0
					],
					[
						69000.0000000001,
						1,
						0
					],
					[
						69214.2857142858,
						3,
						0
					],
					[
						69428.5714285715,
						2,
						0
					],
					[
						69857.1428571429,
						2,
						0
					],
					[
						70071.4285714286,
						2,
						0
					],
					[
						69642.8571428572,
						0,
						0
					],
					[
						68571.4285714286,
						7,
						0
					],
					[
						68678.5714285715,
						6,
						0
					],
					[
						68785.7142857143,
						5,
						0
					],
					[
						68892.8571428572,
						4,
						0
					],
					[
						69000.0000000001,
						6,
						0
					],
					[
						69214.2857142858,
						5,
						0
					],
					[
						69107.1428571429,
						7,
						0
					],
					[
						69321.4285714286,
						6,
						0
					],
					[
						69428.5714285715,
						4,
						0
					],
					[
						69535.7142857143,
						5,
						0
					],
					[
						69642.8571428572,
						6,
						0
					],
					[
						69750.0000000001,
						4,
						0
					],
					[
						69857.1428571429,
						7,
						0
					],
					[
						69964.2857142858,
						5,
						0
					],
					[
						70071.4285714286,
						6,
						0
					],
					[
						70178.5714285715,
						4,
						0
					]
				],
				"typeOfSection": 0,
				"gfSection": false,
				"altAnim": false,
				"mustHitSection": false,
				"changeBPM": false,
				"bpm": 140
			},
			{
				"sectionBeats": 4,
				"sectionNotes": [
					[
						70285.7142857143,
						7,
						321.428571428571
					],
					[
						70821.4285714286,
						3,
						0
					],
					[
						70500,
						0,
						0
					],
					[
						70607.1428571429,
						2,
						0
					],
					[
						70714.2857142857,
						1,
						0
					],
					[
						70928.5714285714,
						0,
						0
					],
					[
						70982.1428571429,
						2,
						0
					],
					[
						71142.8571428571,
						3,
						0
					],
					[
						71357.1428571429,
						1,
						0
					],
					[
						71571.4285714286,
						2,
						0
					],
					[
						71785.7142857143,
						0,
						0
					],
					[
						70285.7142857143,
						4,
						0
					]
				],
				"typeOfSection": 0,
				"gfSection": false,
				"altAnim": false,
				"mustHitSection": true,
				"changeBPM": false,
				"bpm": 140
			},
			{
				"sectionBeats": 4,
				"sectionNotes": [
					[
						72857.1428571429,
						7,
						0
					],
					[
						73071.4285714286,
						4,
						0
					],
					[
						73285.7142857143,
						6,
						0
					],
					[
						73500,
						5,
						0
					],
					[
						72000,
						2,
						0
					],
					[
						72214.2857142857,
						3,
						0
					],
					[
						72428.5714285714,
						1,
						0
					],
					[
						72535.7142857143,
						2,
						0
					],
					[
						72642.8571428571,
						0,
						0
					],
					[
						72857.1428571429,
						3,
						0
					],
					[
						73071.4285714286,
						0,
						0
					],
					[
						73178.5714285714,
						1,
						0
					],
					[
						73285.7142857143,
						2,
						0
					],
					[
						73500,
						1,
						0
					],
					[
						73553.5714285714,
						3,
						0
					]
				],
				"typeOfSection": 0,
				"gfSection": false,
				"altAnim": false,
				"mustHitSection": true,
				"changeBPM": false,
				"bpm": 140
			},
			{
				"sectionBeats": 4,
				"sectionNotes": [
					[
						73714.2857142857,
						7,
						321.428571428571
					],
					[
						73714.2857142857,
						2,
						0
					],
					[
						73928.5714285714,
						1,
						0
					],
					[
						74142.8571428571,
						0,
						0
					],
					[
						74357.1428571429,
						1,
						0
					],
					[
						74464.2857142857,
						2,
						0
					],
					[
						74571.4285714286,
						3,
						0
					],
					[
						74785.7142857143,
						0,
						0
					],
					[
						75000,
						2,
						0
					],
					[
						75214.2857142857,
						3,
						0
					],
					[
						75321.4285714286,
						3,
						0
					]
				],
				"typeOfSection": 0,
				"gfSection": false,
				"altAnim": false,
				"mustHitSection": true,
				"changeBPM": false,
				"bpm": 140
			},
			{
				"sectionBeats": 4,
				"sectionNotes": [
					[
						76285.7142857143,
						4,
						0
					],
					[
						76500,
						6,
						0
					],
					[
						76714.2857142857,
						7,
						0
					],
					[
						76928.5714285714,
						6,
						0
					],
					[
						75428.5714285714,
						1,
						0
					],
					[
						75642.8571428571,
						0,
						0
					],
					[
						75750,
						1,
						0
					],
					[
						75857.1428571429,
						2,
						0
					],
					[
						75964.2857142857,
						1,
						0
					],
					[
						76071.4285714286,
						0,
						0
					],
					[
						76178.5714285714,
						1,
						0
					],
					[
						76285.7142857143,
						3,
						0
					],
					[
						76500,
						3,
						0
					],
					[
						76714.2857142857,
						2,
						0
					],
					[
						76928.5714285714,
						0,
						0
					]
				],
				"typeOfSection": 0,
				"gfSection": false,
				"altAnim": false,
				"mustHitSection": true,
				"changeBPM": false,
				"bpm": 140
			},
			{
				"sectionBeats": 4,
				"sectionNotes": [
					[
						77785.7142857143,
						0,
						0
					],
					[
						78000,
						3,
						0
					],
					[
						78214.2857142857,
						2,
						0
					],
					[
						77142.8571428571,
						1,
						321.428571428571
					],
					[
						78642.8571428571,
						0,
						0
					],
					[
						77142.8571428571,
						0,
						0
					],
					[
						78000,
						1,
						0
					],
					[
						77142.8571428571,
						7,
						0
					],
					[
						77357.1428571429,
						5,
						0
					],
					[
						77571.4285714286,
						7,
						0
					],
					[
						77785.7142857143,
						6,
						0
					],
					[
						78214.2857142857,
						6,
						0
					],
					[
						78000,
						4,
						0
					],
					[
						78428.5714285714,
						5,
						0
					],
					[
						77142.8571428572,
						6,
						0
					],
					[
						77571.4285714286,
						4,
						0
					],
					[
						78000,
						5,
						0
					],
					[
						78428.5714285715,
						7,
						0
					]
				],
				"typeOfSection": 0,
				"gfSection": false,
				"altAnim": false,
				"mustHitSection": false,
				"changeBPM": false,
				"bpm": 140
			},
			{
				"sectionBeats": 4,
				"sectionNotes": [
					[
						79071.4285714286,
						2,
						0
					],
					[
						79500,
						1,
						0
					],
					[
						79928.5714285714,
						3,
						0
					],
					[
						80142.8571428571,
						0,
						0
					],
					[
						80357.1428571429,
						3,
						0
					],
					[
						78857.1428571429,
						6,
						0
					],
					[
						79285.7142857143,
						7,
						0
					],
					[
						79500,
						6,
						0
					],
					[
						79714.2857142857,
						6,
						0
					],
					[
						80142.8571428572,
						1,
						0
					],
					[
						78857.1428571429,
						5,
						0
					],
					[
						79285.7142857143,
						4,
						0
					],
					[
						79714.2857142857,
						4,
						0
					],
					[
						80142.8571428572,
						4,
						0
					],
					[
						80142.8571428572,
						5,
						0
					],
					[
						79928.5714285714,
						7,
						0
					]
				],
				"typeOfSection": 0,
				"gfSection": false,
				"altAnim": false,
				"mustHitSection": false,
				"changeBPM": false,
				"bpm": 140
			},
			{
				"sectionBeats": 4,
				"sectionNotes": [
					[
						80571.4285714286,
						1,
						0
					],
					[
						80785.7142857143,
						1,
						0
					],
					[
						81214.2857142857,
						2,
						0
					],
					[
						81642.8571428571,
						2,
						0
					],
					[
						81857.1428571429,
						1,
						0
					],
					[
						82071.4285714286,
						2,
						0
					],
					[
						81000,
						3,
						0
					],
					[
						81428.5714285714,
						1,
						0
					],
					[
						81857.1428571429,
						0,
						0
					],
					[
						80571.4285714286,
						7,
						0
					],
					[
						80785.7142857143,
						4,
						0
					],
					[
						81000,
						6,
						0
					],
					[
						81214.2857142857,
						4,
						0
					],
					[
						81321.4285714286,
						5,
						0
					],
					[
						81428.5714285714,
						7,
						0
					],
					[
						81857.1428571429,
						7,
						0
					],
					[
						82071.4285714286,
						4,
						0
					],
					[
						80571.4285714286,
						2,
						0
					],
					[
						81000,
						0,
						0
					],
					[
						81428.5714285714,
						3,
						0
					],
					[
						80571.4285714286,
						6,
						0
					],
					[
						81000,
						5,
						0
					],
					[
						81428.5714285714,
						6,
						0
					],
					[
						81642.8571428572,
						4,
						0
					],
					[
						81857.1428571429,
						5,
						0
					],
					[
						81964.2857142857,
						6,
						0
					]
				],
				"typeOfSection": 0,
				"gfSection": false,
				"altAnim": false,
				"mustHitSection": false,
				"changeBPM": false,
				"bpm": 140
			},
			{
				"sectionBeats": 4,
				"sectionNotes": [
					[
						82285.7142857143,
						3,
						0
					],
					[
						82500,
						0,
						0
					],
					[
						82714.2857142857,
						3,
						0
					],
					[
						82928.5714285714,
						0,
						0
					],
					[
						83142.8571428571,
						1,
						0
					],
					[
						83357.1428571428,
						2,
						0
					],
					[
						83571.4285714286,
						3,
						0
					],
					[
						82714.2857142857,
						2,
						0
					],
					[
						83142.8571428571,
						3,
						0
					],
					[
						83571.4285714286,
						0,
						0
					],
					[
						82285.7142857143,
						5,
						0
					],
					[
						82500,
						7,
						0
					],
					[
						82714.2857142857,
						6,
						0
					],
					[
						83357.1428571428,
						6,
						0
					],
					[
						83571.4285714286,
						5,
						0
					],
					[
						83732.1428571428,
						6,
						0
					],
					[
						83839.2857142857,
						7,
						0
					],
					[
						82285.7142857143,
						2,
						0
					],
					[
						82285.7142857143,
						6,
						0
					],
					[
						82714.2857142857,
						4,
						0
					],
					[
						82928.5714285714,
						5,
						0
					],
					[
						83142.8571428572,
						7,
						0
					],
					[
						83142.8571428572,
						4,
						0
					],
					[
						83571.4285714286,
						4,
						0
					]
				],
				"typeOfSection": 0,
				"gfSection": false,
				"altAnim": false,
				"mustHitSection": false,
				"changeBPM": false,
				"bpm": 140
			},
			{
				"sectionBeats": 4,
				"sectionNotes": [
					[
						84428.5714285714,
						0,
						0
					],
					[
						84642.8571428571,
						2,
						0
					],
					[
						84857.1428571428,
						1,
						0
					],
					[
						85071.4285714286,
						1,
						0
					],
					[
						85285.7142857143,
						3,
						0
					],
					[
						85500,
						0,
						0
					],
					[
						84428.5714285714,
						3,
						0
					],
					[
						84857.1428571429,
						0,
						0
					],
					[
						85285.7142857143,
						2,
						0
					]
				],
				"typeOfSection": 0,
				"gfSection": false,
				"altAnim": false,
				"mustHitSection": true,
				"changeBPM": false,
				"bpm": 140
			},
			{
				"sectionBeats": 4,
				"sectionNotes": [
					[
						85714.2857142857,
						1,
						0
					],
					[
						85928.5714285714,
						3,
						0
					],
					[
						86571.4285714286,
						2,
						321.428571428571
					],
					[
						87000,
						1,
						0
					],
					[
						87053.5714285714,
						3,
						0
					],
					[
						87214.2857142857,
						2,
						0
					],
					[
						85714.2857142857,
						2,
						0
					],
					[
						86142.8571428572,
						0,
						0
					],
					[
						86571.4285714286,
						3,
						0
					],
					[
						87000,
						0,
						0
					],
					[
						86142.8571428572,
						2,
						0
					],
					[
						86357.1428571429,
						1,
						0
					]
				],
				"typeOfSection": 0,
				"gfSection": false,
				"altAnim": false,
				"mustHitSection": true,
				"changeBPM": false,
				"bpm": 140
			},
			{
				"sectionBeats": 4,
				"sectionNotes": [
					[
						87428.5714285714,
						0,
						0
					],
					[
						87642.8571428571,
						1,
						0
					],
					[
						87857.1428571428,
						0,
						0
					],
					[
						88071.4285714286,
						2,
						0
					],
					[
						88714.2857142857,
						1,
						0
					],
					[
						87428.5714285714,
						1,
						0
					],
					[
						87857.1428571429,
						3,
						0
					],
					[
						88285.7142857143,
						1,
						0
					],
					[
						88928.5714285714,
						2,
						0
					],
					[
						88285.7142857143,
						0,
						0
					],
					[
						88767.8571428571,
						3,
						0
					],
					[
						88714.2857142857,
						0,
						0
					]
				],
				"typeOfSection": 0,
				"gfSection": false,
				"altAnim": false,
				"mustHitSection": true,
				"changeBPM": false,
				"bpm": 140
			},
			{
				"sectionBeats": 4,
				"sectionNotes": [
					[
						89142.8571428571,
						3,
						0
					],
					[
						89250,
						0,
						0
					],
					[
						89357.1428571428,
						1,
						0
					],
					[
						89892.8571428571,
						1,
						0
					],
					[
						90000,
						2,
						0
					],
					[
						89785.7142857143,
						0,
						0
					],
					[
						89571.4285714286,
						3,
						0
					],
					[
						90428.5714285714,
						1,
						0
					],
					[
						90535.7142857143,
						2,
						0
					],
					[
						89142.8571428571,
						2,
						0
					],
					[
						90000,
						3,
						0
					],
					[
						89571.4285714286,
						1,
						0
					],
					[
						90428.5714285714,
						0,
						0
					]
				],
				"typeOfSection": 0,
				"gfSection": false,
				"altAnim": false,
				"mustHitSection": true,
				"changeBPM": false,
				"bpm": 140
			},
			{
				"sectionBeats": 4,
				"sectionNotes": [
					[
						91285.7142857143,
						3,
						0
					],
					[
						91500,
						0,
						0
					],
					[
						91714.2857142857,
						3,
						321.428571428571
					],
					[
						92142.8571428571,
						1,
						0
					],
					[
						92357.1428571428,
						3,
						0
					],
					[
						92142.8571428571,
						0,
						0
					],
					[
						91714.2857142857,
						2,
						0
					],
					[
						91285.7142857143,
						1,
						0
					],
					[
						90857.1428571429,
						7,
						0
					],
					[
						90857.1428571429,
						5,
						0
					]
				],
				"typeOfSection": 0,
				"gfSection": false,
				"altAnim": false,
				"mustHitSection": false,
				"changeBPM": false,
				"bpm": 140
			},
			{
				"sectionBeats": 4,
				"sectionNotes": [
					[
						92571.4285714286,
						0,
						0
					],
					[
						92785.7142857143,
						1,
						0
					],
					[
						93000,
						0,
						0
					],
					[
						93214.2857142857,
						1,
						0
					],
					[
						93428.5714285714,
						2,
						321.428571428571
					],
					[
						93857.1428571428,
						3,
						0
					],
					[
						94071.4285714286,
						2,
						0
					],
					[
						92571.4285714286,
						2,
						0
					],
					[
						93000,
						3,
						0
					],
					[
						93428.5714285714,
						0,
						0
					],
					[
						93857.1428571429,
						1,
						0
					]
				],
				"typeOfSection": 0,
				"gfSection": false,
				"altAnim": false,
				"mustHitSection": false,
				"changeBPM": false,
				"bpm": 140
			},
			{
				"sectionBeats": 4,
				"sectionNotes": [
					[
						94285.7142857143,
						1,
						0
					],
					[
						94500,
						0,
						0
					],
					[
						94607.1428571428,
						3,
						0
					],
					[
						94714.2857142857,
						1,
						0
					],
					[
						94928.5714285714,
						3,
						0
					],
					[
						95142.8571428571,
						0,
						0
					],
					[
						95357.1428571428,
						3,
						0
					],
					[
						95571.4285714286,
						0,
						0
					],
					[
						95785.7142857143,
						3,
						0
					],
					[
						94285.7142857143,
						0,
						0
					],
					[
						94714.2857142857,
						2,
						0
					],
					[
						95142.8571428571,
						1,
						0
					],
					[
						95571.4285714286,
						1,
						0
					]
				],
				"typeOfSection": 0,
				"gfSection": false,
				"altAnim": false,
				"mustHitSection": false,
				"changeBPM": false,
				"bpm": 140
			},
			{
				"sectionBeats": 4,
				"sectionNotes": [
					[
						96214.2857142857,
						1,
						0
					],
					[
						96857.1428571428,
						2,
						0
					],
					[
						96428.5714285714,
						0,
						0
					],
					[
						96642.8571428571,
						1,
						0
					],
					[
						97285.7142857143,
						3,
						0
					],
					[
						96000,
						0,
						0
					],
					[
						96000,
						2,
						0
					],
					[
						96428.5714285714,
						2,
						0
					],
					[
						96857.1428571428,
						3,
						0
					],
					[
						97285.7142857143,
						0,
						0
					]
				],
				"typeOfSection": 0,
				"gfSection": false,
				"altAnim": false,
				"mustHitSection": false,
				"changeBPM": false,
				"bpm": 140
			},
			{
				"sectionBeats": 4,
				"sectionNotes": [
					[
						97714.2857142857,
						2,
						321.428571428571
					],
					[
						97714.2857142857,
						1,
						0
					]
				],
				"typeOfSection": 0,
				"gfSection": false,
				"altAnim": false,
				"mustHitSection": false,
				"changeBPM": false,
				"bpm": 140
			},
			{
				"sectionBeats": 4,
				"sectionNotes": [],
				"typeOfSection": 0,
				"gfSection": false,
				"altAnim": false,
				"mustHitSection": false,
				"changeBPM": false,
				"bpm": 140
			},
			{
				"sectionBeats": 4,
				"sectionNotes": [],
				"typeOfSection": 0,
				"gfSection": false,
				"altAnim": false,
				"mustHitSection": true,
				"changeBPM": false,
				"bpm": 140
			},
			{
				"sectionBeats": 4,
				"sectionNotes": [],
				"typeOfSection": 0,
				"gfSection": false,
				"altAnim": false,
				"mustHitSection": true,
				"changeBPM": false,
				"bpm": 140
			},
			{
				"sectionBeats": 4,
				"sectionNotes": [],
				"typeOfSection": 0,
				"gfSection": false,
				"altAnim": false,
				"mustHitSection": true,
				"changeBPM": false,
				"bpm": 140
			},
			{
				"sectionBeats": 4,
				"sectionNotes": [],
				"typeOfSection": 0,
				"gfSection": false,
				"altAnim": false,
				"mustHitSection": true,
				"changeBPM": false,
				"bpm": 140
			},
			{
				"sectionBeats": 4,
				"sectionNotes": [],
				"typeOfSection": 0,
				"gfSection": false,
				"altAnim": false,
				"mustHitSection": true,
				"changeBPM": false,
				"bpm": 140
			},
			{
				"sectionBeats": 4,
				"sectionNotes": [],
				"typeOfSection": 0,
				"gfSection": false,
				"altAnim": false,
				"mustHitSection": true,
				"changeBPM": false,
				"bpm": 140
			},
			{
				"sectionBeats": 4,
				"sectionNotes": [],
				"typeOfSection": 0,
				"gfSection": false,
				"altAnim": false,
				"mustHitSection": true,
				"changeBPM": false,
				"bpm": 140
			},
			{
				"sectionBeats": 4,
				"sectionNotes": [],
				"typeOfSection": 0,
				"gfSection": false,
				"altAnim": false,
				"mustHitSection": true,
				"changeBPM": false,
				"bpm": 140
			},
			{
				"sectionBeats": 4,
				"sectionNotes": [],
				"typeOfSection": 0,
				"gfSection": false,
				"altAnim": false,
				"mustHitSection": true,
				"changeBPM": false,
				"bpm": 140
			},
			{
				"sectionBeats": 4,
				"sectionNotes": [],
				"typeOfSection": 0,
				"gfSection": false,
				"altAnim": false,
				"mustHitSection": true,
				"changeBPM": false,
				"bpm": 140
			},
			{
				"typeOfSection": 0,
				"sectionNotes": [],
				"sectionBeats": 4,
				"altAnim": false,
				"gfSection": false,
				"bpm": 140,
				"changeBPM": false,
				"mustHitSection": true
			},
			{
				"typeOfSection": 0,
				"sectionNotes": [],
				"sectionBeats": 4,
				"altAnim": false,
				"gfSection": false,
				"bpm": 140,
				"changeBPM": false,
				"mustHitSection": true
			},
			{
				"typeOfSection": 0,
				"sectionNotes": [],
				"sectionBeats": 4,
				"altAnim": false,
				"gfSection": false,
				"bpm": 140,
				"changeBPM": false,
				"mustHitSection": true
			},
			{
				"typeOfSection": 0,
				"sectionNotes": [],
				"sectionBeats": 4,
				"altAnim": false,
				"gfSection": false,
				"bpm": 140,
				"changeBPM": false,
				"mustHitSection": true
			},
			{
				"sectionBeats": 4,
				"sectionNotes": [],
				"typeOfSection": 0,
				"gfSection": false,
				"altAnim": false,
				"mustHitSection": true,
				"changeBPM": false,
				"bpm": 140
			},
			{
				"sectionBeats": 4,
				"sectionNotes": [],
				"typeOfSection": 0,
				"gfSection": false,
				"altAnim": false,
				"mustHitSection": true,
				"changeBPM": false,
				"bpm": 140
			},
			{
				"sectionBeats": 4,
				"sectionNotes": [],
				"typeOfSection": 0,
				"gfSection": false,
				"altAnim": false,
				"mustHitSection": true,
				"changeBPM": false,
				"bpm": 140
			},
			{
				"sectionBeats": 4,
				"sectionNotes": [],
				"typeOfSection": 0,
				"gfSection": false,
				"altAnim": false,
				"mustHitSection": true,
				"changeBPM": false,
				"bpm": 140
			},
			{
				"typeOfSection": 0,
				"sectionNotes": [],
				"sectionBeats": 4,
				"altAnim": false,
				"gfSection": false,
				"bpm": 140,
				"changeBPM": false,
				"mustHitSection": true
			},
			{
				"typeOfSection": 0,
				"sectionNotes": [],
				"sectionBeats": 4,
				"altAnim": false,
				"gfSection": false,
				"bpm": 140,
				"changeBPM": false,
				"mustHitSection": true
			},
			{
				"typeOfSection": 0,
				"sectionNotes": [],
				"sectionBeats": 4,
				"altAnim": false,
				"gfSection": false,
				"bpm": 140,
				"changeBPM": false,
				"mustHitSection": true
			},
			{
				"typeOfSection": 0,
				"sectionNotes": [],
				"sectionBeats": 4,
				"altAnim": false,
				"gfSection": false,
				"bpm": 140,
				"changeBPM": false,
				"mustHitSection": true
			},
			{
				"typeOfSection": 0,
				"sectionNotes": [],
				"sectionBeats": 4,
				"altAnim": false,
				"gfSection": false,
				"bpm": 140,
				"changeBPM": false,
				"mustHitSection": true
			},
			{
				"typeOfSection": 0,
				"sectionNotes": [],
				"sectionBeats": 4,
				"altAnim": false,
				"gfSection": false,
				"bpm": 140,
				"changeBPM": false,
				"mustHitSection": true
			},
			{
				"typeOfSection": 0,
				"sectionNotes": [],
				"sectionBeats": 4,
				"altAnim": false,
				"gfSection": false,
				"bpm": 140,
				"changeBPM": false,
				"mustHitSection": true
			},
			{
				"typeOfSection": 0,
				"sectionNotes": [],
				"sectionBeats": 4,
				"altAnim": false,
				"gfSection": false,
				"bpm": 140,
				"changeBPM": false,
				"mustHitSection": true
			},
			{
				"typeOfSection": 0,
				"sectionNotes": [],
				"sectionBeats": 4,
				"altAnim": false,
				"gfSection": false,
				"bpm": 140,
				"changeBPM": false,
				"mustHitSection": true
			},
			{
				"typeOfSection": 0,
				"sectionNotes": [],
				"sectionBeats": 4,
				"altAnim": false,
				"gfSection": false,
				"bpm": 140,
				"changeBPM": false,
				"mustHitSection": true
			},
			{
				"typeOfSection": 0,
				"sectionNotes": [],
				"sectionBeats": 4,
				"altAnim": false,
				"gfSection": false,
				"bpm": 140,
				"changeBPM": false,
				"mustHitSection": true
			},
			{
				"typeOfSection": 0,
				"sectionNotes": [],
				"sectionBeats": 4,
				"altAnim": false,
				"gfSection": false,
				"bpm": 140,
				"changeBPM": false,
				"mustHitSection": true
			},
			{
				"typeOfSection": 0,
				"sectionNotes": [],
				"sectionBeats": 4,
				"altAnim": false,
				"gfSection": false,
				"bpm": 140,
				"changeBPM": false,
				"mustHitSection": true
			},
			{
				"typeOfSection": 0,
				"sectionNotes": [],
				"sectionBeats": 4,
				"altAnim": false,
				"gfSection": false,
				"bpm": 140,
				"changeBPM": false,
				"mustHitSection": true
			},
			{
				"typeOfSection": 0,
				"sectionNotes": [],
				"sectionBeats": 4,
				"altAnim": false,
				"gfSection": false,
				"bpm": 140,
				"changeBPM": false,
				"mustHitSection": true
			},
			{
				"typeOfSection": 0,
				"sectionNotes": [],
				"sectionBeats": 4,
				"altAnim": false,
				"gfSection": false,
				"bpm": 140,
				"changeBPM": false,
				"mustHitSection": true
			},
			{
				"sectionBeats": 4,
				"sectionNotes": [],
				"typeOfSection": 0,
				"gfSection": false,
				"altAnim": false,
				"mustHitSection": true,
				"changeBPM": false,
				"bpm": 140
			},
			{
				"sectionBeats": 4,
				"sectionNotes": [],
				"typeOfSection": 0,
				"gfSection": false,
				"altAnim": false,
				"mustHitSection": true,
				"changeBPM": false,
				"bpm": 140
			},
			{
				"sectionBeats": 4,
				"sectionNotes": [],
				"typeOfSection": 0,
				"gfSection": false,
				"altAnim": false,
				"mustHitSection": true,
				"changeBPM": false,
				"bpm": 140
			},
			{
				"sectionBeats": 4,
				"sectionNotes": [],
				"typeOfSection": 0,
				"gfSection": false,
				"altAnim": false,
				"mustHitSection": true,
				"changeBPM": false,
				"bpm": 140
			},
			{
				"typeOfSection": 0,
				"sectionNotes": [],
				"sectionBeats": 4,
				"altAnim": false,
				"gfSection": false,
				"bpm": 140,
				"changeBPM": false,
				"mustHitSection": true
			},
			{
				"typeOfSection": 0,
				"sectionNotes": [],
				"sectionBeats": 4,
				"altAnim": false,
				"gfSection": false,
				"bpm": 140,
				"changeBPM": false,
				"mustHitSection": true
			},
			{
				"typeOfSection": 0,
				"sectionNotes": [],
				"sectionBeats": 4,
				"altAnim": false,
				"gfSection": false,
				"bpm": 140,
				"changeBPM": false,
				"mustHitSection": true
			},
			{
				"sectionBeats": 4,
				"sectionNotes": [],
				"typeOfSection": 0,
				"gfSection": false,
				"altAnim": false,
				"mustHitSection": true,
				"changeBPM": false,
				"bpm": 140
			},
			{
				"sectionBeats": 4,
				"sectionNotes": [],
				"typeOfSection": 0,
				"gfSection": false,
				"altAnim": false,
				"mustHitSection": true,
				"changeBPM": false,
				"bpm": 140
			},
			{
				"sectionBeats": 4,
				"sectionNotes": [],
				"typeOfSection": 0,
				"gfSection": false,
				"altAnim": false,
				"mustHitSection": true,
				"changeBPM": false,
				"bpm": 140
			},
			{
				"sectionBeats": 4,
				"sectionNotes": [],
				"typeOfSection": 0,
				"gfSection": false,
				"altAnim": false,
				"mustHitSection": true,
				"changeBPM": false,
				"bpm": 140
			},
			{
				"sectionBeats": 4,
				"sectionNotes": [],
				"typeOfSection": 0,
				"gfSection": false,
				"altAnim": false,
				"mustHitSection": true,
				"changeBPM": false,
				"bpm": 140
			},
			{
				"sectionBeats": 4,
				"sectionNotes": [],
				"typeOfSection": 0,
				"gfSection": false,
				"altAnim": false,
				"mustHitSection": true,
				"changeBPM": false,
				"bpm": 140
			},
			{
				"typeOfSection": 0,
				"sectionNotes": [],
				"sectionBeats": 4,
				"altAnim": false,
				"gfSection": false,
				"bpm": 140,
				"changeBPM": false,
				"mustHitSection": true
			},
			{
				"sectionBeats": 4,
				"sectionNotes": [],
				"typeOfSection": 0,
				"gfSection": false,
				"altAnim": false,
				"mustHitSection": true,
				"changeBPM": false,
				"bpm": 140
			},
			{
				"sectionBeats": 4,
				"sectionNotes": [],
				"typeOfSection": 0,
				"gfSection": false,
				"altAnim": false,
				"mustHitSection": true,
				"changeBPM": false,
				"bpm": 140
			},
			{
				"sectionBeats": 4,
				"sectionNotes": [],
				"typeOfSection": 0,
				"gfSection": false,
				"altAnim": false,
				"mustHitSection": true,
				"changeBPM": false,
				"bpm": 140
			},
			{
				"sectionBeats": 4,
				"sectionNotes": [],
				"typeOfSection": 0,
				"gfSection": false,
				"altAnim": false,
				"mustHitSection": true,
				"changeBPM": false,
				"bpm": 140
			},
			{
				"sectionBeats": 4,
				"sectionNotes": [],
				"typeOfSection": 0,
				"gfSection": false,
				"altAnim": false,
				"mustHitSection": true,
				"changeBPM": false,
				"bpm": 140
			},
			{
				"sectionBeats": 4,
				"sectionNotes": [],
				"typeOfSection": 0,
				"gfSection": false,
				"altAnim": false,
				"mustHitSection": true,
				"changeBPM": false,
				"bpm": 140
			},
			{
				"sectionBeats": 4,
				"sectionNotes": [],
				"typeOfSection": 0,
				"gfSection": false,
				"altAnim": false,
				"mustHitSection": true,
				"changeBPM": false,
				"bpm": 140
			},
			{
				"sectionBeats": 4,
				"sectionNotes": [],
				"typeOfSection": 0,
				"gfSection": false,
				"altAnim": false,
				"mustHitSection": true,
				"changeBPM": false,
				"bpm": 140
			},
			{
				"sectionBeats": 4,
				"sectionNotes": [],
				"typeOfSection": 0,
				"gfSection": false,
				"altAnim": false,
				"mustHitSection": true,
				"changeBPM": false,
				"bpm": 140
			},
			{
				"sectionBeats": 4,
				"sectionNotes": [],
				"typeOfSection": 0,
				"gfSection": false,
				"altAnim": false,
				"mustHitSection": true,
				"changeBPM": false,
				"bpm": 140
			},
			{
				"sectionBeats": 4,
				"sectionNotes": [],
				"typeOfSection": 0,
				"gfSection": false,
				"altAnim": false,
				"mustHitSection": true,
				"changeBPM": false,
				"bpm": 140
			},
			{
				"sectionBeats": 4,
				"sectionNotes": [],
				"typeOfSection": 0,
				"gfSection": false,
				"altAnim": false,
				"mustHitSection": true,
				"changeBPM": false,
				"bpm": 140
			},
			{
				"sectionBeats": 4,
				"sectionNotes": [],
				"typeOfSection": 0,
				"gfSection": false,
				"altAnim": false,
				"mustHitSection": true,
				"changeBPM": false,
				"bpm": 140
			},
			{
				"sectionBeats": 4,
				"sectionNotes": [],
				"typeOfSection": 0,
				"gfSection": false,
				"altAnim": false,
				"mustHitSection": true,
				"changeBPM": false,
				"bpm": 140
			},
			{
				"sectionBeats": 4,
				"sectionNotes": [],
				"typeOfSection": 0,
				"gfSection": false,
				"altAnim": false,
				"mustHitSection": true,
				"changeBPM": false,
				"bpm": 140
			},
			{
				"sectionBeats": 4,
				"sectionNotes": [],
				"typeOfSection": 0,
				"gfSection": false,
				"altAnim": false,
				"mustHitSection": true,
				"changeBPM": false,
				"bpm": 140
			},
			{
				"typeOfSection": 0,
				"sectionNotes": [],
				"sectionBeats": 4,
				"altAnim": false,
				"gfSection": false,
				"bpm": 140,
				"changeBPM": false,
				"mustHitSection": true
			},
			{
				"typeOfSection": 0,
				"sectionNotes": [],
				"sectionBeats": 4,
				"altAnim": false,
				"gfSection": false,
				"bpm": 140,
				"changeBPM": false,
				"mustHitSection": true
			},
			{
				"sectionBeats": 4,
				"sectionNotes": [],
				"typeOfSection": 0,
				"gfSection": false,
				"altAnim": false,
				"mustHitSection": true,
				"changeBPM": false,
				"bpm": 140
			},
			{
				"sectionBeats": 4,
				"sectionNotes": [],
				"typeOfSection": 0,
				"gfSection": false,
				"altAnim": false,
				"mustHitSection": true,
				"changeBPM": false,
				"bpm": 140
			},
			{
				"sectionBeats": 4,
				"sectionNotes": [],
				"typeOfSection": 0,
				"gfSection": false,
				"altAnim": false,
				"mustHitSection": true,
				"changeBPM": false,
				"bpm": 140
			},
			{
				"sectionBeats": 4,
				"sectionNotes": [],
				"typeOfSection": 0,
				"gfSection": false,
				"altAnim": false,
				"mustHitSection": true,
				"changeBPM": false,
				"bpm": 140
			},
			{
				"sectionBeats": 4,
				"sectionNotes": [],
				"typeOfSection": 0,
				"gfSection": false,
				"altAnim": false,
				"mustHitSection": true,
				"changeBPM": false,
				"bpm": 140
			},
			{
				"sectionBeats": 4,
				"sectionNotes": [],
				"typeOfSection": 0,
				"gfSection": false,
				"altAnim": false,
				"mustHitSection": true,
				"changeBPM": false,
				"bpm": 140
			},
			{
				"typeOfSection": 0,
				"sectionNotes": [],
				"sectionBeats": 4,
				"altAnim": false,
				"gfSection": false,
				"bpm": 140,
				"changeBPM": false,
				"mustHitSection": true
			},
			{
				"typeOfSection": 0,
				"sectionNotes": [],
				"sectionBeats": 4,
				"altAnim": false,
				"gfSection": false,
				"bpm": 140,
				"changeBPM": false,
				"mustHitSection": true
			},
			{
				"sectionBeats": 4,
				"sectionNotes": [],
				"typeOfSection": 0,
				"gfSection": false,
				"altAnim": false,
				"mustHitSection": true,
				"changeBPM": false,
				"bpm": 140
			},
			{
				"sectionBeats": 4,
				"sectionNotes": [],
				"typeOfSection": 0,
				"gfSection": false,
				"altAnim": false,
				"mustHitSection": true,
				"changeBPM": false,
				"bpm": 140
			},
			{
				"typeOfSection": 0,
				"sectionNotes": [],
				"sectionBeats": 4,
				"altAnim": false,
				"gfSection": false,
				"bpm": 140,
				"changeBPM": false,
				"mustHitSection": true
			},
			{
				"typeOfSection": 0,
				"sectionNotes": [],
				"sectionBeats": 4,
				"altAnim": false,
				"gfSection": false,
				"bpm": 140,
				"changeBPM": false,
				"mustHitSection": true
			},
			{
				"typeOfSection": 0,
				"sectionNotes": [],
				"sectionBeats": 4,
				"altAnim": false,
				"gfSection": false,
				"bpm": 140,
				"changeBPM": false,
				"mustHitSection": true
			},
			{
				"typeOfSection": 0,
				"sectionNotes": [],
				"sectionBeats": 4,
				"altAnim": false,
				"gfSection": false,
				"bpm": 140,
				"changeBPM": false,
				"mustHitSection": true
			},
			{
				"typeOfSection": 0,
				"sectionNotes": [],
				"sectionBeats": 4,
				"altAnim": false,
				"gfSection": false,
				"bpm": 140,
				"changeBPM": false,
				"mustHitSection": true
			},
			{
				"typeOfSection": 0,
				"sectionNotes": [],
				"sectionBeats": 4,
				"altAnim": false,
				"gfSection": false,
				"bpm": 140,
				"changeBPM": false,
				"mustHitSection": true
			},
			{
				"typeOfSection": 0,
				"sectionNotes": [],
				"sectionBeats": 4,
				"altAnim": false,
				"gfSection": false,
				"bpm": 140,
				"changeBPM": false,
				"mustHitSection": true
			},
			{
				"typeOfSection": 0,
				"sectionNotes": [],
				"sectionBeats": 4,
				"altAnim": false,
				"gfSection": false,
				"bpm": 140,
				"changeBPM": false,
				"mustHitSection": true
			},
			{
				"typeOfSection": 0,
				"sectionNotes": [],
				"sectionBeats": 4,
				"altAnim": false,
				"gfSection": false,
				"bpm": 140,
				"changeBPM": false,
				"mustHitSection": true
			},
			{
				"typeOfSection": 0,
				"sectionNotes": [],
				"sectionBeats": 4,
				"altAnim": false,
				"gfSection": false,
				"bpm": 140,
				"changeBPM": false,
				"mustHitSection": true
			},
			{
				"typeOfSection": 0,
				"sectionNotes": [],
				"sectionBeats": 4,
				"altAnim": false,
				"gfSection": false,
				"bpm": 140,
				"changeBPM": false,
				"mustHitSection": true
			},
			{
				"typeOfSection": 0,
				"sectionNotes": [],
				"sectionBeats": 4,
				"altAnim": false,
				"gfSection": false,
				"bpm": 140,
				"changeBPM": false,
				"mustHitSection": true
			},
			{
				"typeOfSection": 0,
				"sectionNotes": [],
				"sectionBeats": 4,
				"altAnim": false,
				"gfSection": false,
				"bpm": 140,
				"changeBPM": false,
				"mustHitSection": true
			},
			{
				"typeOfSection": 0,
				"sectionNotes": [],
				"sectionBeats": 4,
				"altAnim": false,
				"gfSection": false,
				"bpm": 140,
				"changeBPM": false,
				"mustHitSection": true
			},
			{
				"typeOfSection": 0,
				"sectionNotes": [],
				"sectionBeats": 4,
				"altAnim": false,
				"gfSection": false,
				"bpm": 140,
				"changeBPM": false,
				"mustHitSection": true
			},
			{
				"typeOfSection": 0,
				"sectionNotes": [],
				"sectionBeats": 4,
				"altAnim": false,
				"gfSection": false,
				"bpm": 140,
				"changeBPM": false,
				"mustHitSection": true
			},
			{
				"typeOfSection": 0,
				"sectionNotes": [],
				"sectionBeats": 4,
				"altAnim": false,
				"gfSection": false,
				"bpm": 140,
				"changeBPM": false,
				"mustHitSection": true
			},
			{
				"typeOfSection": 0,
				"sectionNotes": [],
				"sectionBeats": 4,
				"altAnim": false,
				"gfSection": false,
				"bpm": 140,
				"changeBPM": false,
				"mustHitSection": true
			},
			{
				"typeOfSection": 0,
				"sectionNotes": [],
				"sectionBeats": 4,
				"altAnim": false,
				"gfSection": false,
				"bpm": 140,
				"changeBPM": false,
				"mustHitSection": true
			},
			{
				"sectionBeats": 4,
				"sectionNotes": [],
				"typeOfSection": 0,
				"gfSection": false,
				"altAnim": false,
				"mustHitSection": true,
				"changeBPM": false,
				"bpm": 140
			},
			{
				"sectionBeats": 4,
				"sectionNotes": [],
				"typeOfSection": 0,
				"gfSection": false,
				"altAnim": false,
				"mustHitSection": true,
				"changeBPM": false,
				"bpm": 140
			},
			{
				"sectionBeats": 4,
				"sectionNotes": [],
				"typeOfSection": 0,
				"gfSection": false,
				"altAnim": false,
				"mustHitSection": true,
				"changeBPM": false,
				"bpm": 140
			},
			{
				"sectionBeats": 4,
				"sectionNotes": [],
				"typeOfSection": 0,
				"gfSection": false,
				"altAnim": false,
				"mustHitSection": true,
				"changeBPM": false,
				"bpm": 140
			},
			{
				"sectionBeats": 4,
				"sectionNotes": [],
				"typeOfSection": 0,
				"gfSection": false,
				"altAnim": false,
				"mustHitSection": true,
				"changeBPM": false,
				"bpm": 140
			},
			{
				"gfSection": false,
				"altAnim": false,
				"typeOfSection": 0,
				"sectionNotes": [],
				"bpm": 140,
				"sectionBeats": 4,
				"changeBPM": false,
				"mustHitSection": true
			}
		],
		"events": [
			[
				0,
				[
					[
						"arrowswap",
						"b",
						"0.1"
					],
					[
						"Warning",
						"youarehere",
						"1.7"
					]
				]
			],
			[
				107.142857142857,
				[
					[
						"Play Animation",
						"intro",
						"BF"
					]
				]
			],
			[
				1714.28571428571,
				[
					[
						"Camera Follow Pos",
						"3620",
						"1550"
					],
					[
						"Set Cam Zoom",
						"0.33",
						""
					],
					[
						"Flash Camera",
						"0.6",
						""
					]
				]
			],
			[
				4928.57142857143,
				[
					[
						"Add Camera Zoom",
						"0.02",
						""
					]
				]
			],
			[
				5142.85714285714,
				[
					[
						"Add Camera Zoom",
						"0.02",
						""
					]
				]
			],
			[
				7714.28571428571,
				[
					[
						"Add Camera Zoom",
						"0.025",
						""
					]
				]
			],
			[
				8142.85714285714,
				[
					[
						"Add Camera Zoom",
						"0.025",
						""
					]
				]
			],
			[
				8571.42857142857,
				[
					[
						"Add Camera Zoom",
						"0.032",
						""
					]
				]
			],
			[
				9000,
				[
					[
						"Add Camera Zoom",
						"0.032",
						""
					]
				]
			],
			[
				9428.57142857143,
				[
					[
						"Add Camera Zoom",
						"0.032",
						""
					]
				]
			],
			[
				9857.14285714286,
				[
					[
						"Add Camera Zoom",
						"0.032",
						""
					]
				]
			],
			[
				10285.7142857143,
				[
					[
						"Add Camera Zoom",
						"0.032",
						""
					]
				]
			],
			[
				10714.2857142857,
				[
					[
						"Add Camera Zoom",
						"0.032",
						""
					]
				]
			],
			[
				11142.8571428571,
				[
					[
						"Add Camera Zoom",
						"0.032",
						""
					]
				]
			],
			[
				11571.4285714286,
				[
					[
						"Add Camera Zoom",
						"0.032",
						""
					]
				]
			],
			[
				12000,
				[
					[
						"Add Camera Zoom",
						"0.032",
						""
					]
				]
			],
			[
				12428.5714285714,
				[
					[
						"Add Camera Zoom",
						"0.032",
						""
					]
				]
			],
			[
				12857.1428571429,
				[
					[
						"Add Camera Zoom",
						"0.032",
						""
					]
				]
			],
			[
				13285.7142857143,
				[
					[
						"Add Camera Zoom",
						"0.032",
						""
					]
				]
			],
			[
				13714.2857142857,
				[
					[
						"Add Camera Zoom",
						"0.032",
						""
					]
				]
			],
			[
				14142.8571428571,
				[
					[
						"Add Camera Zoom",
						"0.032",
						""
					]
				]
			],
			[
				14571.4285714286,
				[
					[
						"Add Camera Zoom",
						"0.032",
						""
					]
				]
			],
			[
				15000,
				[
					[
						"Add Camera Zoom",
						"0.032",
						""
					]
				]
			],
			[
				16285.7142857143,
				[
					[
						"Add Camera Zoom",
						"0.06",
						""
					]
				]
			],
			[
				18000,
				[
					[
						"Add Camera Zoom",
						"0.06",
						""
					]
				]
			],
			[
				19714.2857142857,
				[
					[
						"Add Camera Zoom",
						"0.06",
						""
					]
				]
			],
			[
				21428.5714285714,
				[
					[
						"Add Camera Zoom",
						"0.06",
						""
					]
				]
			],
			[
				23142.8571428571,
				[
					[
						"Add Camera Zoom",
						"0.06",
						""
					]
				]
			],
			[
				24857.1428571429,
				[
					[
						"Add Camera Zoom",
						"0.06",
						""
					]
				]
			],
			[
				26571.4285714286,
				[
					[
						"Add Camera Zoom",
						"0.06",
						""
					]
				]
			],
			[
				28285.7142857143,
				[
					[
						"Add Camera Zoom",
						"0.06",
						""
					]
				]
			],
			[
				30000,
				[
					[
						"Add Camera Zoom",
						"0.06",
						""
					]
				]
			],
			[
				31714.2857142857,
				[
					[
						"Add Camera Zoom",
						"0.06",
						""
					]
				]
			],
			[
				33428.5714285714,
				[
					[
						"Add Camera Zoom",
						"0.06",
						""
					]
				]
			],
			[
				35142.8571428571,
				[
					[
						"Add Camera Zoom",
						"0.06",
						""
					]
				]
			],
			[
				36857.1428571429,
				[
					[
						"Add Camera Zoom",
						"0.06",
						""
					]
				]
			],
			[
				38571.4285714286,
				[
					[
						"Add Camera Zoom",
						"0.06",
						""
					]
				]
			],
			[
				40285.7142857143,
				[
					[
						"Add Camera Zoom",
						"0.06",
						""
					]
				]
			],
			[
				42000,
				[
					[
						"Add Camera Zoom",
						"0.06",
						""
					]
				]
			],
			[
				42857.1428571429,
				[
					[
						"Flash Camera",
						"0.8",
						""
					],
					[
						"Change Character",
						"0",
						"wakusonic-chase"
					],
					[
						"Camera Follow Pos",
						"",
						""
					],
					[
						"Change Character",
						"1",
						"wakubf-chase"
					]
				]
			],
			[
				43392.8571428572,
				[
					[
						"Play Animation",
						"jump",
						"Dad"
					]
				]
			],
			[
				43714.2857142857,
				[
					[
						"Add Camera Zoom",
						"0.06",
						""
					]
				]
			],
			[
				45428.5714285714,
				[
					[
						"Add Camera Zoom",
						"0.06",
						""
					]
				]
			],
			[
				46821.4285714286,
				[
					[
						"Play Animation",
						"jump",
						"Dad"
					]
				]
			],
			[
				47142.8571428571,
				[
					[
						"Add Camera Zoom",
						"0.06",
						""
					]
				]
			],
			[
				48857.1428571429,
				[
					[
						"Add Camera Zoom",
						"0.06",
						""
					]
				]
			],
			[
				50571.4285714286,
				[
					[
						"Add Camera Zoom",
						"0.06",
						""
					]
				]
			],
			[
				52285.7142857143,
				[
					[
						"Add Camera Zoom",
						"0.06",
						""
					]
				]
			],
			[
				54000,
				[
					[
						"Add Camera Zoom",
						"0.06",
						""
					]
				]
			],
			[
				55714.2857142857,
				[
					[
						"Add Camera Zoom",
						"0.06",
						""
					]
				]
			],
			[
				56357.1428571429,
				[
					[
						"Play Animation",
						"jump",
						"Dad"
					]
				]
			],
			[
				57428.5714285714,
				[
					[
						"Add Camera Zoom",
						"0.06",
						""
					]
				]
			],
			[
				59142.8571428571,
				[
					[
						"Add Camera Zoom",
						"0.06",
						""
					]
				]
			],
			[
				60857.1428571429,
				[
					[
						"Add Camera Zoom",
						"0.06",
						""
					]
				]
			],
			[
				62571.4285714286,
				[
					[
						"Add Camera Zoom",
						"0.06",
						""
					]
				]
			],
			[
				64285.7142857143,
				[
					[
						"Add Camera Zoom",
						"0.06",
						""
					]
				]
			],
			[
				66000,
				[
					[
						"Add Camera Zoom",
						"0.06",
						""
					]
				]
			],
			[
				67714.2857142857,
				[
					[
						"Add Camera Zoom",
						"0.06",
						""
					]
				]
			],
			[
				70821.4285714286,
				[
					[
						"Play Animation",
						"jump",
						"Dad"
					]
				]
			],
			[
				74250,
				[
					[
						"Play Animation",
						"jump",
						"Dad"
					]
				]
			],
			[
				77142.8571428572,
				[
					[
						"Add Camera Zoom",
						"0.032",
						""
					]
				]
			],
			[
				77571.4285714286,
				[
					[
						"Add Camera Zoom",
						"0.032",
						""
					]
				]
			],
			[
				78000,
				[
					[
						"Add Camera Zoom",
						"0.032",
						""
					]
				]
			],
			[
				78428.5714285715,
				[
					[
						"Add Camera Zoom",
						"0.032",
						""
					]
				]
			],
			[
				78857.1428571429,
				[
					[
						"Add Camera Zoom",
						"0.032",
						""
					]
				]
			],
			[
				79285.7142857143,
				[
					[
						"Add Camera Zoom",
						"0.032",
						""
					]
				]
			],
			[
				79714.2857142857,
				[
					[
						"Add Camera Zoom",
						"0.032",
						""
					]
				]
			],
			[
				80142.8571428572,
				[
					[
						"Add Camera Zoom",
						"0.032",
						""
					]
				]
			],
			[
				80571.4285714286,
				[
					[
						"Add Camera Zoom",
						"0.032",
						""
					]
				]
			],
			[
				81000,
				[
					[
						"Add Camera Zoom",
						"0.032",
						""
					]
				]
			],
			[
				81428.5714285715,
				[
					[
						"Add Camera Zoom",
						"0.032",
						""
					]
				]
			],
			[
				81857.1428571429,
				[
					[
						"Add Camera Zoom",
						"0.032",
						""
					]
				]
			],
			[
				82285.7142857143,
				[
					[
						"Add Camera Zoom",
						"0.032",
						""
					]
				]
			],
			[
				82714.2857142858,
				[
					[
						"Add Camera Zoom",
						"0.032",
						""
					]
				]
			],
			[
				83142.8571428572,
				[
					[
						"Add Camera Zoom",
						"0.032",
						""
					]
				]
			],
			[
				83571.4285714286,
				[
					[
						"Add Camera Zoom",
						"0.032",
						""
					]
				]
			],
			[
				83785.7142857143,
				[
					[
						"Play Animation",
						"jump",
						"Dad"
					]
				]
			],
			[
				84000,
				[
					[
						"Add Camera Zoom",
						"0.032",
						""
					]
				]
			],
			[
				84428.5714285715,
				[
					[
						"Add Camera Zoom",
						"0.032",
						""
					]
				]
			],
			[
				84857.1428571429,
				[
					[
						"Add Camera Zoom",
						"0.032",
						""
					]
				]
			],
			[
				85285.7142857143,
				[
					[
						"Add Camera Zoom",
						"0.032",
						""
					]
				]
			],
			[
				85714.2857142857,
				[
					[
						"Add Camera Zoom",
						"0.032",
						""
					]
				]
			],
			[
				86142.8571428572,
				[
					[
						"Add Camera Zoom",
						"0.032",
						""
					]
				]
			],
			[
				86571.4285714286,
				[
					[
						"Add Camera Zoom",
						"0.032",
						""
					]
				]
			],
			[
				87000,
				[
					[
						"Add Camera Zoom",
						"0.032",
						""
					]
				]
			],
			[
				87428.5714285715,
				[
					[
						"Add Camera Zoom",
						"0.032",
						""
					]
				]
			],
			[
				87857.1428571429,
				[
					[
						"Add Camera Zoom",
						"0.032",
						""
					]
				]
			],
			[
				88285.7142857143,
				[
					[
						"Add Camera Zoom",
						"0.032",
						""
					]
				]
			],
			[
				88714.2857142858,
				[
					[
						"Add Camera Zoom",
						"0.032",
						""
					]
				]
			],
			[
				89142.8571428572,
				[
					[
						"Add Camera Zoom",
						"0.032",
						""
					]
				]
			],
			[
				89571.4285714286,
				[
					[
						"Add Camera Zoom",
						"0.032",
						""
					]
				]
			],
			[
				90000,
				[
					[
						"Add Camera Zoom",
						"0.032",
						""
					]
				]
			],
			[
				90428.5714285715,
				[
					[
						"Add Camera Zoom",
						"0.032",
						""
					]
				]
			],
			[
				90857.1428571429,
				[
					[
						"Add Camera Zoom",
						"0.032",
						""
					]
				]
			],
			[
				91285.7142857143,
				[
					[
						"Add Camera Zoom",
						"0.032",
						""
					]
				]
			],
			[
				91714.2857142857,
				[
					[
						"Add Camera Zoom",
						"0.032",
						""
					]
				]
			],
			[
				92142.8571428572,
				[
					[
						"Add Camera Zoom",
						"0.032",
						""
					]
				]
			],
			[
				92571.4285714286,
				[
					[
						"Add Camera Zoom",
						"0.032",
						""
					]
				]
			],
			[
				93000,
				[
					[
						"Add Camera Zoom",
						"0.032",
						""
					]
				]
			],
			[
				93428.5714285714,
				[
					[
						"Add Camera Zoom",
						"0.032",
						""
					]
				]
			],
			[
				93857.1428571429,
				[
					[
						"Add Camera Zoom",
						"0.032",
						""
					]
				]
			],
			[
				94285.7142857143,
				[
					[
						"Add Camera Zoom",
						"0.032",
						""
					]
				]
			],
			[
				94714.2857142858,
				[
					[
						"Add Camera Zoom",
						"0.032",
						""
					]
				]
			],
			[
				95142.8571428572,
				[
					[
						"Add Camera Zoom",
						"0.032",
						""
					]
				]
			],
			[
				95571.4285714286,
				[
					[
						"Add Camera Zoom",
						"0.032",
						""
					]
				]
			],
			[
				96000,
				[
					[
						"Add Camera Zoom",
						"0.032",
						""
					]
				]
			],
			[
				96428.5714285715,
				[
					[
						"Add Camera Zoom",
						"0.032",
						""
					]
				]
			],
			[
				96857.1428571429,
				[
					[
						"Add Camera Zoom",
						"0.032",
						""
					]
				]
			],
			[
				97285.7142857143,
				[
					[
						"Add Camera Zoom",
						"0.032",
						""
					]
				]
			],
			[
				97714.2857142857,
				[
					[
						"Add Camera Zoom",
						"0.2",
						"0.06"
					]
				]
			],
			[
				98250,
				[
					[
						"Play Animation",
						"jump",
						"Dad"
					],
					[
						"Camera Follow Pos",
						"3600",
						"1600"
					]
				]
			],
			[
				98464.2857142857,
				[
					[
						"OpponentMove",
						"3900",
						"-600"
					]
				]
			],
			[
				98892.8571428571,
				[
					[
						"PlayerMove",
						"3200",
						"-600"
					]
				]
			]
		],
		"player2": "bf",
		"splashSkin": "wakuSplashes",
		"song": "speed criminal",
		"needsVoices": true,
		"arrowSkin": "",
		"stage": "stage",
		"validScore": true,
		"bpm": 140,
		"speed": 2.7
	}
}